MANIFEST.in
README.rst
setup.py
ESGConfigParser/__init__.py
ESGConfigParser/constants.py
ESGConfigParser/custom_exceptions.py
ESGConfigParser.egg-info/PKG-INFO
ESGConfigParser.egg-info/SOURCES.txt
ESGConfigParser.egg-info/dependency_links.txt
ESGConfigParser.egg-info/not-zip-safe
ESGConfigParser.egg-info/top_level.txt