Metadata-Version: 1.1
Name: ESGConfigParser
Version: 0.1.12
Summary: ESGF configuration ESGConfigParser for INI files
Home-page: https://github.com/ESGF/config/tree/master/publisher-configs/ESGConfigParser
Author: Levavasseur Guillaume
Author-email: glipsl@ipsl.fr
License: UNKNOWN
Platform: Unix
Classifier: Development Status :: 5 - Production/Stable
Classifier: Environment :: Console
Classifier: Intended Audience :: Science/Research
Classifier: Intended Audience :: System Administrators
Classifier: Natural Language :: English
Classifier: Operating System :: Unix
Classifier: Programming Language :: Python
Classifier: Topic :: Scientific/Engineering
Classifier: Topic :: Software Development :: Build Tools
